latent_viewer/__init__.py
latent_viewer/run_viewer.py
latent_viewer/viewer.py
latent_viewer-0.0.1.dist-info/METADATA
latent_viewer-0.0.1.dist-info/WHEEL
latent_viewer-0.0.1.dist-info/entry_points.txt
latent_viewer-0.0.1.dist-info/licenses/LICENSE
latent_viewer-0.0.1.dist-info/RECORD
