Metadata-Version: 2.4
Name: latent-viewer
Version: 0.0.1
Summary: An interactive 3D viewer for inspecting image embeddings
Project-URL: Homepage, https://github.com/CLEAR-AI-ML-for-shipping-data/latent-viewer
Project-URL: Issues, https://github.com/CLEAR-AI-ML-for-shipping-data/latent-viewer/issues
Author-email: Leon Boschman <leon.boschman@chalmers.se>
License-Expression: GPL-2.0-or-later
License-File: LICENSE
Requires-Python: >=3.10
Requires-Dist: dash-bootstrap-components>=1.6.0
Requires-Dist: dash>=3.0.4
Requires-Dist: h5py>=3.11.0
Requires-Dist: loguru>=0.7.3
Requires-Dist: numpy>=1.24.4
Requires-Dist: openpyxl>=3.1.5
Requires-Dist: pandas>=2.0.3
Requires-Dist: plotly>=6.0.1
Requires-Dist: scikit-activeml>=0.2.2
Requires-Dist: scikit-learn>=1.3.2
Provides-Extra: dev
Requires-Dist: pre-commit>=4.2.0; extra == 'dev'
Requires-Dist: twine>=6.1.0; extra == 'dev'
